ECAuth0Backend/__init__.py
ECAuth0Backend/apps.py
ECAuth0Backend/backend.py
ECAuth0Backend/jwt.py
ECAuth0Backend/models.py
ECAuth0Backend/settings.py
ECAuth0Backend/tests.py
ECAuth0Backend/urls.py
ECAuth0Backend/views.py
ECAuth0Backend/migrations/0001_initial.py
ECAuth0Backend/migrations/__init__.py
ECAuth0Backend-0.1.2.dist-info/DESCRIPTION.rst
ECAuth0Backend-0.1.2.dist-info/METADATA
ECAuth0Backend-0.1.2.dist-info/RECORD
ECAuth0Backend-0.1.2.dist-info/WHEEL
ECAuth0Backend-0.1.2.dist-info/metadata.json
ECAuth0Backend-0.1.2.dist-info/top_level.txt
