Metadata-Version: 2.0
Name: ECAuth0Backend
Version: 0.1.2
Summary: Django app to authenticate with code or JWT for DjangoRestFramework
Home-page: https://bitbucket.org/ephemerecreative/django-auth0-backend
Author: Raphaël Titsworth-Morin
Author-email: raphael@ephemerecreative.ca
License: MIT License
Platform: UNKNOWN
Classifier: Environment :: Web Environment
Classifier: Framework :: Django
Classifier: Framework :: Django :: 1.11
Classifier: Intended Audience :: Developers
Classifier: License :: OSI Approved :: MIT License
Classifier: Operating System :: OS Independent
Classifier: Programming Language :: Python
Classifier: Programming Language :: Python :: 3.5
Classifier: Programming Language :: Python :: 3.6
Classifier: Topic :: Internet :: WWW/HTTP
Classifier: Topic :: Internet :: WWW/HTTP :: Dynamic Content
